odoo/addons/purchase_order_product_recommendation_secondary_unit/README.rst
odoo/addons/purchase_order_product_recommendation_secondary_unit/__init__.py
odoo/addons/purchase_order_product_recommendation_secondary_unit/__manifest__.py
odoo/addons/purchase_order_product_recommendation_secondary_unit/i18n/es.po
odoo/addons/purchase_order_product_recommendation_secondary_unit/i18n/purchase_order_product_recommendation_secondary_unit.pot
odoo/addons/purchase_order_product_recommendation_secondary_unit/readme/CONTRIBUTORS.rst
odoo/addons/purchase_order_product_recommendation_secondary_unit/readme/DESCRIPTION.rst
odoo/addons/purchase_order_product_recommendation_secondary_unit/readme/USAGE.rst
odoo/addons/purchase_order_product_recommendation_secondary_unit/static/description/icon.png
odoo/addons/purchase_order_product_recommendation_secondary_unit/static/description/index.html
odoo/addons/purchase_order_product_recommendation_secondary_unit/wizards/__init__.py
odoo/addons/purchase_order_product_recommendation_secondary_unit/wizards/purchase_order_recommendation.py
odoo/addons/purchase_order_product_recommendation_secondary_unit/wizards/purchase_order_recommendation_view.xml
odoo11_addon_purchase_order_product_recommendation_secondary_unit-11.0.1.0.0.99.dev6.dist-info/METADATA
odoo11_addon_purchase_order_product_recommendation_secondary_unit-11.0.1.0.0.99.dev6.dist-info/WHEEL
odoo11_addon_purchase_order_product_recommendation_secondary_unit-11.0.1.0.0.99.dev6.dist-info/top_level.txt
odoo11_addon_purchase_order_product_recommendation_secondary_unit-11.0.1.0.0.99.dev6.dist-info/RECORD
